{
    "face": 21539,
    "leopard": 2246,
    "motorbike": 986,
    "accordion": 436,
    "airplane": 5480,
    "anchor": 948,
    "ant": 831,
    "barrel": 1918,
    "bass": 1248,
    "beaver": 377,
    "binocular": 784,
    "bonsai": 555,
    "brain": 5956,
    "brontosaurus": 13,
    "buddha": 148,
    "butterfly": 8231,
    "camera": 15169,
    "cannon": 544,
    "car_side": 99,
    "ceiling_fan": 681,
    "cellphone": 614,
    "chair": 33369,
    "chandelier": 3537,
    "cougar_body": 5,
    "cougar_face": 5,
    "crab": 1822,
    "crayfish": 106,
    "crocodile": 1760,
    "crocodile_head": 52,
    "cup": 20205,
    "dalmatian": 83,
    "dollar_bill": 1877,
    "dolphin": 2735,
    "dragonfly": 542,
    "electric_guitar": 257,
    "elephant": 8568,
    "emu": 157,
    "euphonium": 33,
    "ewer": 23,
    "ferry": 1280,
    "flamingo": 1163,
    "flamingo_head": 20,
    "garfield": 0,
    "gerenuk": 0,
    "gramophone": 63,
    "grand_piano": 4,
    "hawksbill": 0,
    "headphone": 3957,
    "hedgehog": 1210,
    "helicopter": 5914,
    "ibis": 27,
    "inline_skate": 18,
    "joshua_tree": 263,
    "kangaroo": 933,
    "ketch": 47,
    "lamp": 7289,
    "laptop": 18265,
    "llama": 997,
    "lobster": 765,
    "lotus": 1437,
    "mandolin": 42,
    "mayfly": 2,
    "menorah": 155,
    "metronome": 0,
    "minaret": 331,
    "nautilus": 17,
    "octopus": 1320,
    "okapi": 20,
    "pagoda": 562,
    "panda": 2792,
    "pigeon": 1087,
    "pizza": 6490,
    "platypus": 60,
    "pyramid": 3006,
    "revolver": 94,
    "rhino": 663,
    "rooster": 1451,
    "saxophone": 784,
    "schooner": 11,
    "scissors": 1971,
    "scorpion": 510,
    "sea_horse": 89,
    "snoopy": 0,
    "soccer_ball": 3682,
    "stapler": 51,
    "starfish": 1080,
    "stegosaurus": 1,
    "stop_sign": 528,
    "strawberry": 6290,
    "sunflower": 4180,
    "tick": 244,
    "trilobite": 5,
    "umbrella": 7284,
    "watch": 10647,
    "water_lilly": 9,
    "wheelchair": 3325,
    "wild_cat": 1,
    "windsor_chair": 0,
    "wrench": 853,
    "yin_yang": 116
}