{
    "abyssinian": 0,
    "american_bulldog": 2147,
    "american_pit_bull_terrier": 65,
    "basset_hound": 528,
    "beagle": 2664,
    "bengal": 0,
    "birman": 461,
    "bombay": 0,
    "boxer": 5390,
    "british_shorthair": 0,
    "chihuahua": 2033,
    "egyptian_mau": 0,
    "english_cocker_spaniel": 573,
    "english_setter": 187,
    "german_shorthaired": 0,
    "great_pyrenees": 2,
    "havanese": 470,
    "japanese_chin": 2,
    "keeshond": 2,
    "leonberger": 0,
    "maine_coon": 12,
    "miniature_pinscher": 208,
    "newfoundland": 0,
    "persian": 0,
    "pomeranian": 431,
    "pug": 2471,
    "ragdoll": 134,
    "russian_blue": 59,
    "saint_bernard": 24,
    "samoyed": 111,
    "scottish_terrier": 11,
    "shiba_inu": 211,
    "siamese": 1021,
    "sphynx": 7,
    "staffordshire_bull_terrier": 15,
    "wheaten_terrier": 2,
    "yorkshire_terrier": 43
}