{
    "abbey": 46397,
    "airplane_cabin": 2436,
    "airport_terminal": 30738,
    "alley": 191422,
    "amphitheater": 21592,
    "amusement_arcade": 11468,
    "amusement_park": 75295,
    "anechoic_chamber": 213,
    "outdoor apartment_building": 28152,
    "indoor apse": 49380,
    "aquarium": 80329,
    "aqueduct": 6109,
    "arch": 211810,
    "archive": 3785,
    "outdoor arrival_gate": 27355,
    "art_gallery": 79374,
    "art_school": 439,
    "art_studio": 4523,
    "assembly_line": 12353,
    "outdoor athletic_field": 130777,
    "public atrium": 110498,
    "attic": 22928,
    "auditorium": 338002,
    "auto_factory": 0,
    "badlands": 1288,
    "indoor badminton_court": 896,
    "baggage_claim": 23903,
    "shop bakery": 17025,
    "exterior balcony": 163895,
    "interior balcony": 48666,
    "ball_pit": 1077,
    "ballroom": 19399,
    "bamboo_forest": 5823,
    "banquet_hall": 24396,
    "bar": 277975,
    "barn": 181060,
    "barndoor": 887,
    "baseball_field": 109837,
    "basement": 39876,
    "basilica": 84465,
    "outdoor basketball_court": 70219,
    "bathroom": 183876,
    "batters_box": 7293,
    "bayou": 21225,
    "indoor bazaar": 10221,
    "outdoor bazaar": 11424,
    "beach": 799783,
    "beauty_salon": 787,
    "bedroom": 69515,
    "berth": 0,
    "biology_laboratory": 0,
    "indoor bistro": 101947,
    "boardwalk": 169217,
    "boat_deck": 0,
    "boathouse": 59459,
    "bookstore": 44380,
    "indoor booth": 23055,
    "botanical_garden": 0,
    "indoor bow_window": 5,
    "outdoor bow_window": 0,
    "bowling_alley": 9189,
    "boxing_ring": 5854,
    "indoor brewery": 1775,
    "bridge": 677842,
    "building_facade": 109,
    "bullring": 1134,
    "burial_chamber": 140,
    "bus_interior": 16,
    "butchers_shop": 3,
    "butte": 7071,
    "outdoor cabin": 116968,
    "cafeteria": 53985,
    "campsite": 28820,
    "campus": 54083,
    "natural canal": 163176,
    "urban canal": 35004,
    "candy_store": 1780,
    "canyon": 103281,
    "backseat car_interior": 5,
    "frontseat car_interior": 0,
    "carrousel": 12546,
    "indoor casino": 9267,
    "castle": 212101,
    "catacomb": 40,
    "indoor cathedral": 110519,
    "outdoor cathedral": 112323,
    "indoor cavern": 15368,
    "cemetery": 123930,
    "chalet": 853,
    "cheese_factory": 101,
    "chemistry_lab": 504,
    "indoor chicken_coop": 2151,
    "outdoor chicken_coop": 4578,
    "childs_room": 0,
    "indoor church": 118792,
    "outdoor church": 97696,
    "classroom": 277994,
    "clean_room": 0,
    "cliff": 404164,
    "indoor cloister": 34591,
    "closet": 179658,
    "clothing_store": 20216,
    "coast": 675231,
    "cockpit": 22735,
    "coffee_shop": 20878,
    "computer_room": 6034,
    "conference_center": 655,
    "conference_room": 224665,
    "construction_site": 80180,
    "control_room": 200,
    "outdoor control_tower": 6446,
    "corn_field": 5161,
    "corral": 12989,
    "corridor": 147303,
    "cottage_garden": 844,
    "courthouse": 31194,
    "courtroom": 11281,
    "courtyard": 682739,
    "exterior covered_bridge": 7260,
    "creek": 271847,
    "crevasse": 6163,
    "crosswalk": 119983,
    "office cubicle": 22991,
    "dam": 32994,
    "delicatessen": 848,
    "dentists_office": 1412,
    "sand desert": 127109,
    "vegetation desert": 181489,
    "indoor diner": 476,
    "outdoor diner": 241,
    "home dinette": 13680,
    "vehicle dinette": 864,
    "dining_car": 24652,
    "dining_room": 110824,
    "discotheque": 14,
    "dock": 574441,
    "outdoor doorway": 101004,
    "dorm_room": 9196,
    "driveway": 494728,
    "outdoor driving_range": 385,
    "drugstore": 86461,
    "electrical_substation": 781,
    "door elevator": 6299,
    "interior elevator": 9411,
    "elevator_shaft": 679,
    "engine_room": 1012,
    "indoor escalator": 27787,
    "excavation": 2121,
    "indoor factory": 0,
    "fairway": 26477,
    "fastfood_restaurant": 0,
    "cultivated field": 55377,
    "wild field": 329897,
    "fire_escape": 11294,
    "fire_station": 14135,
    "indoor firing_range": 5,
    "fishpond": 4590,
    "indoor florist_shop": 4717,
    "food_court": 15678,
    "broadleaf forest": 103860,
    "needleleaf forest": 1014,
    "forest_path": 9921,
    "forest_road": 1164,
    "formal_garden": 0,
    "fountain": 232273,
    "galley": 1651,
    "game_room": 1058,
    "indoor garage": 114707,
    "garbage_dump": 8350,
    "gas_station": 34568,
    "exterior gazebo": 52472,
    "indoor general_store": 3,
    "outdoor general_store": 3,
    "gift_shop": 335,
    "golf_course": 39382,
    "indoor greenhouse": 8278,
    "outdoor greenhouse": 13398,
    "indoor gymnasium": 149250,
    "indoor hangar": 31310,
    "outdoor hangar": 34433,
    "harbor": 244329,
    "hayfield": 1633,
    "heliport": 209,
    "herb_garden": 6501,
    "highway": 440470,
    "hill": 1673442,
    "home_office": 6120,
    "hospital": 10694,
    "hospital_room": 7182,
    "hot_spring": 0,
    "outdoor hot_tub": 1045,
    "outdoor hotel": 7172,
    "hotel_room": 65098,
    "house": 1708145,
    "outdoor hunting_lodge": 0,
    "ice_cream_parlor": 1738,
    "ice_floe": 388,
    "ice_shelf": 0,
    "indoor ice_skating_rink": 4867,
    "outdoor ice_skating_rink": 12820,
    "iceberg": 5379,
    "igloo": 4347,
    "industrial_area": 0,
    "outdoor inn": 694,
    "islet": 100913,
    "indoor jacuzzi": 1483,
    "indoor jail": 2875,
    "jail_cell": 4094,
    "jewelry_shop": 887,
    "kasbah": 0,
    "indoor kennel": 3580,
    "outdoor kennel": 4079,
    "kindergarden_classroom": 1,
    "kitchen": 257154,
    "kitchenette": 44396,
    "outdoor labyrinth": 12104,
    "natural lake": 426595,
    "landfill": 501,
    "landing_deck": 1305,
    "laundromat": 727,
    "lecture_room": 17994,
    "indoor library": 99294,
    "outdoor library": 7753,
    "outdoor lido_deck": 1991,
    "lift_bridge": 3605,
    "lighthouse": 108046,
    "limousine_interior": 87,
    "living_room": 228908,
    "lobby": 52778,
    "lock_chamber": 0,
    "locker_room": 14521,
    "mansion": 35635,
    "manufactured_home": 267,
    "indoor market": 15459,
    "outdoor market": 29355,
    "marsh": 49368,
    "martial_arts_gym": 0,
    "mausoleum": 8469,
    "medina": 233,
    "water moat": 21290,
    "outdoor monastery": 2746,
    "indoor mosque": 15360,
    "outdoor mosque": 25299,
    "motel": 56772,
    "mountain": 953646,
    "mountain_snowy": 0,
    "indoor movie_theater": 6707,
    "indoor museum": 250644,
    "music_store": 101458,
    "music_studio": 7065,
    "outdoor nuclear_power_plant": 1463,
    "nursery": 2356,
    "oast_house": 6,
    "outdoor observatory": 2005,
    "ocean": 974869,
    "office": 390762,
    "office_building": 397457,
    "outdoor oil_refinery": 2769,
    "oilrig": 0,
    "operating_room": 969,
    "orchard": 2814,
    "outdoor outhouse": 25520,
    "pagoda": 42770,
    "palace": 138312,
    "pantry": 4304,
    "park": 2958994,
    "indoor parking_garage": 47288,
    "outdoor parking_garage": 49924,
    "parking_lot": 414661,
    "parlor": 30513,
    "pasture": 238169,
    "patio": 175287,
    "pavilion": 51780,
    "pharmacy": 2355,
    "phone_booth": 27371,
    "physics_laboratory": 0,
    "picnic_area": 10393,
    "indoor pilothouse": 1182,
    "outdoor planetarium": 686,
    "playground": 65452,
    "playroom": 2229,
    "plaza": 423495,
    "indoor podium": 176612,
    "outdoor podium": 100261,
    "pond": 369152,
    "establishment poolroom": 222,
    "home poolroom": 166,
    "outdoor power_plant": 9422,
    "promenade_deck": 5705,
    "indoor pub": 17274,
    "pulpit": 36886,
    "putting_green": 22758,
    "racecourse": 20922,
    "raceway": 131390,
    "raft": 83345,
    "railroad_track": 156458,
    "rainforest": 56858,
    "reception": 44146,
    "recreation_room": 6,
    "residential_neighborhood": 0,
    "restaurant": 748116,
    "restaurant_kitchen": 5593,
    "restaurant_patio": 30,
    "rice_paddy": 7220,
    "riding_arena": 4909,
    "river": 1373893,
    "rock_arch": 3063,
    "rope_bridge": 5347,
    "ruin": 195240,
    "runway": 71364,
    "sandbar": 101,
    "sandbox": 2345,
    "sauna": 1055,
    "schoolhouse": 47,
    "sea_cliff": 135763,
    "server_room": 3275,
    "shed": 121685,
    "shoe_shop": 852,
    "shopfront": 249,
    "indoor shopping_mall": 88008,
    "shower": 19688,
    "skatepark": 30850,
    "ski_lodge": 870,
    "ski_resort": 8952,
    "ski_slope": 43968,
    "sky": 3056953,
    "skyscraper": 371054,
    "slum": 7350,
    "snowfield": 0,
    "squash_court": 13209,
    "stable": 18304,
    "baseball stadium": 109062,
    "football stadium": 26155,
    "indoor stage": 493865,
    "staircase": 83730,
    "street": 2647252,
    "subway_interior": 1152,
    "platform subway_station": 38410,
    "supermarket": 35353,
    "sushi_bar": 1271,
    "swamp": 85603,
    "indoor swimming_pool": 19912,
    "outdoor swimming_pool": 35811,
    "indoor synagogue": 5198,
    "outdoor synagogue": 3487,
    "television_studio": 27,
    "east_asia temple": 0,
    "south_asia temple": 5436,
    "indoor tennis_court": 8780,
    "outdoor tennis_court": 19517,
    "outdoor tent": 220335,
    "indoor_procenium theater": 128056,
    "indoor_seats theater": 5128,
    "thriftshop": 7569,
    "throne_room": 1048,
    "ticket_booth": 7301,
    "toll_plaza": 27937,
    "topiary_garden": 394,
    "tower": 1221595,
    "toyshop": 2002,
    "outdoor track": 133800,
    "train_railway": 160008,
    "platform train_station": 93256,
    "tree_farm": 68,
    "tree_house": 12914,
    "trench": 25301,
    "coral_reef underwater": 22593,
    "utility_room": 288,
    "valley": 384209,
    "van_interior": 153,
    "vegetable_garden": 5631,
    "veranda": 231170,
    "veterinarians_office": 0,
    "viaduct": 3648,
    "videostore": 5350,
    "village": 190142,
    "vineyard": 21862,
    "volcano": 10337,
    "indoor volleyball_court": 2628,
    "outdoor volleyball_court": 11,
    "waiting_room": 15455,
    "indoor warehouse": 26801,
    "water_tower": 44577,
    "block waterfall": 137363,
    "fan waterfall": 127198,
    "plunge waterfall": 125891,
    "watering_hole": 1723,
    "wave": 450053,
    "wet_bar": 0,
    "wheat_field": 10982,
    "wind_farm": 4623,
    "windmill": 18639,
    "barrel_storage wine_cellar": 3470,
    "bottle_storage wine_cellar": 2001,
    "indoor wrestling_ring": 3135,
    "yard": 859750,
    "youth_hostel": 0
}