{
    "abbey": 721,
    "airplane_cabin": 52,
    "airport_terminal": 3356,
    "alley": 9460,
    "amphitheater": 7415,
    "amusement_arcade": 90,
    "amusement_park": 2467,
    "anechoic_chamber": 7,
    "outdoor apartment_building": 0,
    "indoor apse": 0,
    "aquarium": 9689,
    "aqueduct": 472,
    "arch": 12977,
    "archive": 716,
    "outdoor arrival_gate": 0,
    "art_gallery": 7323,
    "art_school": 0,
    "art_studio": 10901,
    "assembly_line": 7958,
    "outdoor athletic_field": 0,
    "public atrium": 0,
    "attic": 741,
    "auditorium": 7964,
    "auto_factory": 0,
    "badlands": 27,
    "indoor badminton_court": 0,
    "baggage_claim": 257,
    "shop bakery": 51,
    "exterior balcony": 0,
    "interior balcony": 1,
    "ball_pit": 59,
    "ballroom": 15069,
    "bamboo_forest": 5352,
    "banquet_hall": 550,
    "bar": 18277,
    "barn": 31099,
    "barndoor": 0,
    "baseball_field": 7594,
    "basement": 625,
    "basilica": 1421,
    "outdoor basketball_court": 0,
    "bathroom": 11053,
    "batters_box": 2,
    "bayou": 223,
    "indoor bazaar": 0,
    "outdoor bazaar": 0,
    "beach": 228449,
    "beauty_salon": 3,
    "bedroom": 5593,
    "berth": 0,
    "biology_laboratory": 0,
    "indoor bistro": 0,
    "boardwalk": 1327,
    "boat_deck": 0,
    "boathouse": 177,
    "bookstore": 4666,
    "indoor booth": 0,
    "botanical_garden": 0,
    "indoor bow_window": 0,
    "outdoor bow_window": 0,
    "bowling_alley": 504,
    "boxing_ring": 28,
    "indoor brewery": 0,
    "bridge": 55482,
    "building_facade": 0,
    "bullring": 0,
    "burial_chamber": 2,
    "bus_interior": 0,
    "butchers_shop": 0,
    "butte": 0,
    "outdoor cabin": 5,
    "cafeteria": 942,
    "campsite": 2789,
    "campus": 14700,
    "natural canal": 0,
    "urban canal": 0,
    "candy_store": 130,
    "canyon": 2583,
    "backseat car_interior": 0,
    "frontseat car_interior": 0,
    "carrousel": 59,
    "indoor casino": 0,
    "castle": 58507,
    "catacomb": 0,
    "indoor cathedral": 0,
    "outdoor cathedral": 0,
    "indoor cavern": 0,
    "cemetery": 5599,
    "chalet": 415,
    "cheese_factory": 4,
    "chemistry_lab": 13,
    "indoor chicken_coop": 0,
    "outdoor chicken_coop": 0,
    "childs_room": 0,
    "indoor church": 0,
    "outdoor church": 0,
    "classroom": 35344,
    "clean_room": 0,
    "cliff": 87049,
    "indoor cloister": 0,
    "closet": 1150,
    "clothing_store": 1461,
    "coast": 3685,
    "cockpit": 3411,
    "coffee_shop": 932,
    "computer_room": 209,
    "conference_center": 0,
    "conference_room": 9617,
    "construction_site": 15119,
    "control_room": 129,
    "outdoor control_tower": 0,
    "corn_field": 825,
    "corral": 132,
    "corridor": 1504,
    "cottage_garden": 1209,
    "courthouse": 417,
    "courtroom": 23241,
    "courtyard": 46588,
    "exterior covered_bridge": 0,
    "creek": 4175,
    "crevasse": 222,
    "crosswalk": 784,
    "office cubicle": 379,
    "dam": 1996,
    "delicatessen": 2,
    "dentists_office": 145,
    "sand desert": 28966,
    "vegetation desert": 999,
    "indoor diner": 0,
    "outdoor diner": 0,
    "home dinette": 0,
    "vehicle dinette": 0,
    "dining_car": 0,
    "dining_room": 5,
    "discotheque": 0,
    "dock": 21777,
    "outdoor doorway": 0,
    "dorm_room": 222,
    "driveway": 4454,
    "outdoor driving_range": 0,
    "drugstore": 298,
    "electrical_substation": 0,
    "door elevator": 32,
    "interior elevator": 3,
    "elevator_shaft": 0,
    "engine_room": 0,
    "indoor escalator": 0,
    "excavation": 12,
    "indoor factory": 0,
    "fairway": 5723,
    "fastfood_restaurant": 0,
    "cultivated field": 0,
    "wild field": 1,
    "fire_escape": 36,
    "fire_station": 121,
    "indoor firing_range": 0,
    "fishpond": 31,
    "indoor florist_shop": 1,
    "food_court": 493,
    "broadleaf forest": 20,
    "needleleaf forest": 1,
    "forest_path": 57,
    "forest_road": 0,
    "formal_garden": 0,
    "fountain": 42977,
    "galley": 1,
    "game_room": 124,
    "indoor garage": 0,
    "garbage_dump": 45,
    "gas_station": 4329,
    "exterior gazebo": 0,
    "indoor general_store": 0,
    "outdoor general_store": 0,
    "gift_shop": 0,
    "golf_course": 4860,
    "indoor greenhouse": 0,
    "outdoor greenhouse": 2,
    "indoor gymnasium": 0,
    "indoor hangar": 0,
    "outdoor hangar": 0,
    "harbor": 75018,
    "hayfield": 0,
    "heliport": 0,
    "herb_garden": 453,
    "highway": 10281,
    "hill": 184824,
    "home_office": 1725,
    "hospital": 43975,
    "hospital_room": 11071,
    "hot_spring": 0,
    "outdoor hot_tub": 0,
    "outdoor hotel": 0,
    "hotel_room": 432,
    "house": 254172,
    "outdoor hunting_lodge": 0,
    "ice_cream_parlor": 4,
    "ice_floe": 51,
    "ice_shelf": 0,
    "indoor ice_skating_rink": 0,
    "outdoor ice_skating_rink": 0,
    "iceberg": 3051,
    "igloo": 316,
    "industrial_area": 0,
    "outdoor inn": 0,
    "islet": 304,
    "indoor jacuzzi": 0,
    "indoor jail": 0,
    "jail_cell": 30,
    "jewelry_shop": 11,
    "kasbah": 0,
    "indoor kennel": 0,
    "outdoor kennel": 0,
    "kindergarden_classroom": 0,
    "kitchen": 200486,
    "kitchenette": 185,
    "outdoor labyrinth": 0,
    "natural lake": 0,
    "landfill": 630,
    "landing_deck": 0,
    "laundromat": 145,
    "lecture_room": 7,
    "indoor library": 0,
    "outdoor library": 0,
    "outdoor lido_deck": 0,
    "lift_bridge": 0,
    "lighthouse": 9584,
    "limousine_interior": 0,
    "living_room": 18,
    "lobby": 2428,
    "lock_chamber": 0,
    "locker_room": 2338,
    "mansion": 13566,
    "manufactured_home": 0,
    "indoor market": 0,
    "outdoor market": 3,
    "marsh": 10344,
    "martial_arts_gym": 0,
    "mausoleum": 146,
    "medina": 0,
    "water moat": 268,
    "outdoor monastery": 0,
    "indoor mosque": 0,
    "outdoor mosque": 0,
    "motel": 103,
    "mountain": 176411,
    "mountain_snowy": 0,
    "indoor movie_theater": 0,
    "indoor museum": 0,
    "music_store": 76,
    "music_studio": 1580,
    "outdoor nuclear_power_plant": 0,
    "nursery": 293,
    "oast_house": 0,
    "outdoor observatory": 0,
    "ocean": 62505,
    "office": 139804,
    "office_building": 4,
    "outdoor oil_refinery": 0,
    "oilrig": 0,
    "operating_room": 0,
    "orchard": 4822,
    "outdoor outhouse": 0,
    "pagoda": 5672,
    "palace": 16636,
    "pantry": 1481,
    "park": 100340,
    "indoor parking_garage": 0,
    "outdoor parking_garage": 0,
    "parking_lot": 1149,
    "parlor": 1897,
    "pasture": 23102,
    "patio": 12813,
    "pavilion": 4417,
    "pharmacy": 3146,
    "phone_booth": 539,
    "physics_laboratory": 0,
    "picnic_area": 12,
    "indoor pilothouse": 0,
    "outdoor planetarium": 0,
    "playground": 3578,
    "playroom": 328,
    "plaza": 11288,
    "indoor podium": 0,
    "outdoor podium": 1,
    "pond": 670828,
    "establishment poolroom": 0,
    "home poolroom": 0,
    "outdoor power_plant": 0,
    "promenade_deck": 0,
    "indoor pub": 0,
    "pulpit": 241,
    "putting_green": 0,
    "racecourse": 778,
    "raceway": 6,
    "raft": 2754,
    "railroad_track": 857,
    "rainforest": 29453,
    "reception": 471,
    "recreation_room": 0,
    "residential_neighborhood": 0,
    "restaurant": 15969,
    "restaurant_kitchen": 297,
    "restaurant_patio": 0,
    "rice_paddy": 22687,
    "riding_arena": 0,
    "river": 134931,
    "rock_arch": 30,
    "rope_bridge": 194,
    "ruin": 104528,
    "runway": 24430,
    "sandbar": 0,
    "sandbox": 517,
    "sauna": 2885,
    "schoolhouse": 0,
    "sea_cliff": 7847,
    "server_room": 1878,
    "shed": 231,
    "shoe_shop": 0,
    "shopfront": 0,
    "indoor shopping_mall": 0,
    "shower": 1765,
    "skatepark": 723,
    "ski_lodge": 12,
    "ski_resort": 359,
    "ski_slope": 722,
    "sky": 238805,
    "skyscraper": 6464,
    "slum": 916,
    "snowfield": 0,
    "squash_court": 24,
    "stable": 279,
    "baseball stadium": 8851,
    "football stadium": 1433,
    "indoor stage": 0,
    "staircase": 2975,
    "street": 270860,
    "subway_interior": 0,
    "platform subway_station": 197,
    "supermarket": 7977,
    "sushi_bar": 195,
    "swamp": 4542,
    "indoor swimming_pool": 0,
    "outdoor swimming_pool": 0,
    "indoor synagogue": 0,
    "outdoor synagogue": 0,
    "television_studio": 0,
    "east_asia temple": 0,
    "south_asia temple": 0,
    "indoor tennis_court": 0,
    "outdoor tennis_court": 0,
    "outdoor tent": 6,
    "indoor_procenium theater": 0,
    "indoor_seats theater": 0,
    "thriftshop": 1,
    "throne_room": 3731,
    "ticket_booth": 4,
    "toll_plaza": 107,
    "topiary_garden": 0,
    "tower": 43836,
    "toyshop": 72,
    "outdoor track": 2,
    "train_railway": 2372,
    "platform train_station": 2621,
    "tree_farm": 0,
    "tree_house": 343,
    "trench": 2851,
    "coral_reef underwater": 2,
    "utility_room": 0,
    "valley": 37326,
    "van_interior": 0,
    "vegetable_garden": 582,
    "veranda": 1418,
    "veterinarians_office": 0,
    "viaduct": 74,
    "videostore": 0,
    "village": 197790,
    "vineyard": 57233,
    "volcano": 2638,
    "indoor volleyball_court": 0,
    "outdoor volleyball_court": 0,
    "waiting_room": 6,
    "indoor warehouse": 0,
    "water_tower": 355,
    "block waterfall": 5,
    "fan waterfall": 31,
    "plunge waterfall": 248,
    "watering_hole": 23,
    "wave": 111144,
    "wet_bar": 0,
    "wheat_field": 9357,
    "wind_farm": 1640,
    "windmill": 11633,
    "barrel_storage wine_cellar": 4,
    "bottle_storage wine_cellar": 1,
    "indoor wrestling_ring": 0,
    "yard": 5917,
    "youth_hostel": 0
}